Metadata-Version: 2.1
Name: mbomb
Version: 1.0.0
Summary: MBomb(Gmail To Gmail) Mail Bombing! Send Unlimited Bombing on Inbox!
Home-page: https://github.com/palahsu/MBomb
Author: Palahsu
Author-email: jk3502072@gmail.com
License: LGPLv3
Download-URL: https://github.com/palahsu/MBomb.git
Keywords: mbomb,mail-bomb,mail-bombing,palahsu,bombing,exploit,tool,unlimited-message,message,hacker-scripts,hacking-tool,hacking,vulnerability,bomber,cybersecurity,cyber-security,information-security,securitymessages
Platform: UNKNOWN
Classifier: Environment :: Console
Classifier: Intended Audience :: End Users/Desktop
Classifier: Intended Audience :: Developers
Classifier: Intended Audience :: System Administrators
Classifier: License :: OSI Approved :: GNU General Public License v3 (GPLv3)
Classifier: Programming Language :: Python :: 3
Classifier: Programming Language :: Python :: 3.7
